alt_text_llm/__init__.py
alt_text_llm/apply.py
alt_text_llm/generate.py
alt_text_llm/label.py
alt_text_llm/main.py
alt_text_llm/scan.py
alt_text_llm/utils.py
alt_text_llm-1.2.dist-info/licenses/LICENSE
alt_text_llm-1.2.dist-info/METADATA
alt_text_llm-1.2.dist-info/WHEEL
alt_text_llm-1.2.dist-info/entry_points.txt
alt_text_llm-1.2.dist-info/top_level.txt
alt_text_llm-1.2.dist-info/RECORD
