Metadata-Version: 2.4
Name: alt-text-llm
Version: 1.2
Summary: AI-powered accessibility text generation and labeling tools for markdown content
Author: TurnTrout
License-Expression: MIT
Project-URL: Repository, https://github.com/alexander-turner/alt-text-llm
Keywords: alt-text,accessibility,markdown,llm,ai
Requires-Python: >=3.11
License-File: LICENSE
Requires-Dist: gitpython
Requires-Dist: requests
Requires-Dist: ruamel.yaml
Requires-Dist: markdown-it-py
Requires-Dist: rich
Requires-Dist: tqdm
Requires-Dist: prompt_toolkit
Requires-Dist: beautifulsoup4
Provides-Extra: dev
Requires-Dist: pytest; extra == "dev"
Requires-Dist: mypy; extra == "dev"
Requires-Dist: types-requests; extra == "dev"
Requires-Dist: pytest-asyncio; extra == "dev"
Dynamic: license-file
